MANIFEST.in
README.md
setup.py
examples/album_and_book.py
examples/album_remote.py
examples/metrics.py
regaindapi/__init__.py
regaindapi.egg-info/PKG-INFO
regaindapi.egg-info/SOURCES.txt
regaindapi.egg-info/dependency_links.txt
regaindapi.egg-info/requires.txt
regaindapi.egg-info/top_level.txt