Metadata-Version: 1.1
Name: regaindapi
Version: 0.1.7
Summary: Regaind API python bindings
Home-page: https://github.com/Regaind/regaind-api
Author: Regaind
Author-email: hello@regaind.io
License: MIT
Platform: UNKNOWN
Classifier: Development Status :: 4 - Beta
Classifier: Environment :: Web Environment
Classifier: Intended Audience :: Developers
Classifier: License :: OSI Approved :: BSD License
Classifier: Operating System :: OS Independent
Classifier: Programming Language :: Python
Classifier: Programming Language :: Python :: 2
Classifier: Programming Language :: Python :: 2.7
Classifier: Programming Language :: Python :: 3
Classifier: Topic :: Software Development :: Libraries :: Python Modules
Classifier: Natural Language :: English
